[
  {
    "algo": "HNSW",
    "M": 32,
    "efConstruction": 40,
    "efSearch": 10,
    "build_s": 163.0516580320109,
    "size_mb": 10341.63600730896,
    "rss_mb": 10504.38671875,
    "rss_peak_mb": 20761.609375,
    "rss_delta_mb": 10212.81640625,
    "faiss_threads": 8,
    "qps": 18226.638280318013,
    "latency_ms": 0.0548575459998877,
    "latency_p99_ms": 0.0551074382321676,
    "recall_1": 0.9332,
    "recall_10": 0.89918,
    "recall_100": 0.72184,
    "n_base": 1281167,
    "study": "varyEFC"
  },
  {
    "algo": "HNSW",
    "M": 32,
    "efConstruction": 40,
    "efSearch": 20,
    "build_s": 163.0516580320109,
    "size_mb": 10341.63600730896,
    "rss_mb": 10504.38671875,
    "rss_peak_mb": 20761.609375,
    "rss_delta_mb": 10212.81640625,
    "faiss_threads": 8,
    "qps": 12492.598510048363,
    "latency_ms": 0.0804477149339315,
    "latency_p99_ms": 0.0812648004448274,
    "recall_1": 0.9694,
    "recall_10": 0.95362,
    "recall_100": 0.851268,
    "n_base": 1281167,
    "study": "varyEFC"
  },
  {
    "algo": "HNSW",
    "M": 32,
    "efConstruction": 40,
    "efSearch": 40,
    "build_s": 163.0516580320109,
    "size_mb": 10341.63600730896,
    "rss_mb": 10504.38671875,
    "rss_peak_mb": 20761.609375,
    "rss_delta_mb": 10212.81640625,
    "faiss_threads": 8,
    "qps": 8102.051679809956,
    "latency_ms": 0.1234182140004122,
    "latency_p99_ms": 0.1237977798080537,
    "recall_1": 0.9856,
    "recall_10": 0.97964,
    "recall_100": 0.933702,
    "n_base": 1281167,
    "study": "varyEFC"
  },
  {
    "algo": "HNSW",
    "M": 32,
    "efConstruction": 40,
    "efSearch": 80,
    "build_s": 163.0516580320109,
    "size_mb": 10341.63600730896,
    "rss_mb": 10504.38671875,
    "rss_peak_mb": 20761.609375,
    "rss_delta_mb": 10212.81640625,
    "faiss_threads": 8,
    "qps": 5184.174593744619,
    "latency_ms": 0.1925024991331156,
    "latency_p99_ms": 0.1929739351312746,
    "recall_1": 0.993,
    "recall_10": 0.99144,
    "recall_100": 0.973716,
    "n_base": 1281167,
    "study": "varyEFC"
  },
  {
    "algo": "HNSW",
    "M": 32,
    "efConstruction": 40,
    "efSearch": 160,
    "build_s": 163.0516580320109,
    "size_mb": 10341.63600730896,
    "rss_mb": 10504.38671875,
    "rss_peak_mb": 20761.609375,
    "rss_delta_mb": 10212.81640625,
    "faiss_threads": 8,
    "qps": 3172.5169878626307,
    "latency_ms": 0.3156401617326386,
    "latency_p99_ms": 0.3170134110819781,
    "recall_1": 0.9966,
    "recall_10": 0.9961,
    "recall_100": 0.990228,
    "n_base": 1281167,
    "study": "varyEFC"
  },
  {
    "algo": "HNSW",
    "M": 32,
    "efConstruction": 40,
    "efSearch": 320,
    "build_s": 163.0516580320109,
    "size_mb": 10341.63600730896,
    "rss_mb": 10504.38671875,
    "rss_peak_mb": 20761.609375,
    "rss_delta_mb": 10212.81640625,
    "faiss_threads": 8,
    "qps": 1936.963766524592,
    "latency_ms": 0.5261207633991337,
    "latency_p99_ms": 0.5481310124131851,
    "recall_1": 0.9978,
    "recall_10": 0.9983,
    "recall_100": 0.996586,
    "n_base": 1281167,
    "study": "varyEFC"
  },
  {
    "algo": "HNSW",
    "M": 32,
    "efConstruction": 40,
    "efSearch": 640,
    "build_s": 163.0516580320109,
    "size_mb": 10341.63600730896,
    "rss_mb": 10504.38671875,
    "rss_peak_mb": 20761.609375,
    "rss_delta_mb": 10212.81640625,
    "faiss_threads": 8,
    "qps": 1058.886659634328,
    "latency_ms": 0.94785066320037,
    "latency_p99_ms": 0.9563554946159128,
    "recall_1": 0.999,
    "recall_10": 0.99928,
    "recall_100": 0.998884,
    "n_base": 1281167,
    "study": "varyEFC"
  },
  {
    "algo": "HNSW",
    "M": 32,
    "efConstruction": 100,
    "efSearch": 10,
    "build_s": 215.3759064820042,
    "size_mb": 10341.63600730896,
    "rss_mb": 10456.8828125,
    "rss_peak_mb": 17110.12109375,
    "rss_delta_mb": 10184.3828125,
    "faiss_threads": 8,
    "qps": 26058.21485306248,
    "latency_ms": 0.0384566577345443,
    "latency_p99_ms": 0.0386941730006947,
    "recall_1": 0.9014,
    "recall_10": 0.857,
    "recall_100": 0.606492,
    "n_base": 1281167,
    "study": "varyEFC"
  },
  {
    "algo": "HNSW",
    "M": 32,
    "efConstruction": 100,
    "efSearch": 20,
    "build_s": 215.3759064820042,
    "size_mb": 10341.63600730896,
    "rss_mb": 10456.8828125,
    "rss_peak_mb": 17110.12109375,
    "rss_delta_mb": 10184.3828125,
    "faiss_threads": 8,
    "qps": 17637.305435485712,
    "latency_ms": 0.0566578728001332,
    "latency_p99_ms": 0.0567137006451957,
    "recall_1": 0.9558,
    "recall_10": 0.93442,
    "recall_100": 0.77109,
    "n_base": 1281167,
    "study": "varyEFC"
  },
  {
    "algo": "HNSW",
    "M": 32,
    "efConstruction": 100,
    "efSearch": 40,
    "build_s": 215.3759064820042,
    "size_mb": 10341.63600730896,
    "rss_mb": 10456.8828125,
    "rss_peak_mb": 17110.12109375,
    "rss_delta_mb": 10184.3828125,
    "faiss_threads": 8,
    "qps": 11365.546498700543,
    "latency_ms": 0.087901225600702,
    "latency_p99_ms": 0.0880721495316829,
    "recall_1": 0.9802,
    "recall_10": 0.97172,
    "recall_100": 0.898364,
    "n_base": 1281167,
    "study": "varyEFC"
  },
  {
    "algo": "HNSW",
    "M": 32,
    "efConstruction": 100,
    "efSearch": 80,
    "build_s": 215.3759064820042,
    "size_mb": 10341.63600730896,
    "rss_mb": 10456.8828125,
    "rss_peak_mb": 17110.12109375,
    "rss_delta_mb": 10184.3828125,
    "faiss_threads": 8,
    "qps": 7219.096359017952,
    "latency_ms": 0.138873015200564,
    "latency_p99_ms": 0.1398786205025972,
    "recall_1": 0.992,
    "recall_10": 0.98858,
    "recall_100": 0.963028,
    "n_base": 1281167,
    "study": "varyEFC"
  },
  {
    "algo": "HNSW",
    "M": 32,
    "efConstruction": 100,
    "efSearch": 160,
    "build_s": 215.3759064820042,
    "size_mb": 10341.63600730896,
    "rss_mb": 10456.8828125,
    "rss_peak_mb": 17110.12109375,
    "rss_delta_mb": 10184.3828125,
    "faiss_threads": 8,
    "qps": 4386.706442708112,
    "latency_ms": 0.2277975265334438,
    "latency_p99_ms": 0.228106874139572,
    "recall_1": 0.9966,
    "recall_10": 0.99554,
    "recall_100": 0.987626,
    "n_base": 1281167,
    "study": "varyEFC"
  },
  {
    "algo": "HNSW",
    "M": 32,
    "efConstruction": 100,
    "efSearch": 320,
    "build_s": 215.3759064820042,
    "size_mb": 10341.63600730896,
    "rss_mb": 10456.8828125,
    "rss_peak_mb": 17110.12109375,
    "rss_delta_mb": 10184.3828125,
    "faiss_threads": 8,
    "qps": 2644.582112655004,
    "latency_ms": 0.3811740999333172,
    "latency_p99_ms": 0.387411240085843,
    "recall_1": 0.9988,
    "recall_10": 0.99844,
    "recall_100": 0.996028,
    "n_base": 1281167,
    "study": "varyEFC"
  },
  {
    "algo": "HNSW",
    "M": 32,
    "efConstruction": 100,
    "efSearch": 640,
    "build_s": 215.3759064820042,
    "size_mb": 10341.63600730896,
    "rss_mb": 10456.8828125,
    "rss_peak_mb": 17110.12109375,
    "rss_delta_mb": 10184.3828125,
    "faiss_threads": 8,
    "qps": 1457.1411097071762,
    "latency_ms": 0.6857342798660587,
    "latency_p99_ms": 0.686830347567331,
    "recall_1": 0.9994,
    "recall_10": 0.99942,
    "recall_100": 0.99885,
    "n_base": 1281167,
    "study": "varyEFC"
  },
  {
    "algo": "HNSW",
    "M": 32,
    "efConstruction": 200,
    "efSearch": 10,
    "build_s": 418.3467333409935,
    "size_mb": 10341.63600730896,
    "rss_mb": 10433.296875,
    "rss_peak_mb": 20627.62890625,
    "rss_delta_mb": 10157.60546875,
    "faiss_threads": 8,
    "qps": 24276.353814906972,
    "latency_ms": 0.0413327426019047,
    "latency_p99_ms": 0.0418298666052869,
    "recall_1": 0.9184,
    "recall_10": 0.87648,
    "recall_100": 0.626552,
    "n_base": 1281167,
    "study": "varyEFC"
  },
  {
    "algo": "HNSW",
    "M": 32,
    "efConstruction": 200,
    "efSearch": 20,
    "build_s": 418.3467333409935,
    "size_mb": 10341.63600730896,
    "rss_mb": 10433.296875,
    "rss_peak_mb": 20627.62890625,
    "rss_delta_mb": 10157.60546875,
    "faiss_threads": 8,
    "qps": 16196.541900190296,
    "latency_ms": 0.0617013375333044,
    "latency_p99_ms": 0.0617567195205483,
    "recall_1": 0.9672,
    "recall_10": 0.94808,
    "recall_100": 0.791646,
    "n_base": 1281167,
    "study": "varyEFC"
  },
  {
    "algo": "HNSW",
    "M": 32,
    "efConstruction": 200,
    "efSearch": 40,
    "build_s": 418.3467333409935,
    "size_mb": 10341.63600730896,
    "rss_mb": 10433.296875,
    "rss_peak_mb": 20627.62890625,
    "rss_delta_mb": 10157.60546875,
    "faiss_threads": 8,
    "qps": 10136.949519079466,
    "latency_ms": 0.0986609072657302,
    "latency_p99_ms": 0.0993313212101347,
    "recall_1": 0.987,
    "recall_10": 0.9806,
    "recall_100": 0.915366,
    "n_base": 1281167,
    "study": "varyEFC"
  },
  {
    "algo": "HNSW",
    "M": 32,
    "efConstruction": 200,
    "efSearch": 80,
    "build_s": 418.3467333409935,
    "size_mb": 10341.63600730896,
    "rss_mb": 10433.296875,
    "rss_peak_mb": 20627.62890625,
    "rss_delta_mb": 10157.60546875,
    "faiss_threads": 8,
    "qps": 6369.658501651633,
    "latency_ms": 0.1574962218670407,
    "latency_p99_ms": 0.1587211971518118,
    "recall_1": 0.995,
    "recall_10": 0.99342,
    "recall_100": 0.973488,
    "n_base": 1281167,
    "study": "varyEFC"
  },
  {
    "algo": "HNSW",
    "M": 32,
    "efConstruction": 200,
    "efSearch": 160,
    "build_s": 418.3467333409935,
    "size_mb": 10341.63600730896,
    "rss_mb": 10433.296875,
    "rss_peak_mb": 20627.62890625,
    "rss_delta_mb": 10157.60546875,
    "faiss_threads": 8,
    "qps": 3829.699483427337,
    "latency_ms": 0.2607956861330118,
    "latency_p99_ms": 0.261450883764308,
    "recall_1": 0.9978,
    "recall_10": 0.99774,
    "recall_100": 0.992336,
    "n_base": 1281167,
    "study": "varyEFC"
  },
  {
    "algo": "HNSW",
    "M": 32,
    "efConstruction": 200,
    "efSearch": 320,
    "build_s": 418.3467333409935,
    "size_mb": 10341.63600730896,
    "rss_mb": 10433.296875,
    "rss_peak_mb": 20627.62890625,
    "rss_delta_mb": 10157.60546875,
    "faiss_threads": 8,
    "qps": 2284.906242597102,
    "latency_ms": 0.4362503846651331,
    "latency_p99_ms": 0.4385667679582257,
    "recall_1": 0.9992,
    "recall_10": 0.99908,
    "recall_100": 0.997854,
    "n_base": 1281167,
    "study": "varyEFC"
  },
  {
    "algo": "HNSW",
    "M": 32,
    "efConstruction": 200,
    "efSearch": 640,
    "build_s": 418.3467333409935,
    "size_mb": 10341.63600730896,
    "rss_mb": 10433.296875,
    "rss_peak_mb": 20627.62890625,
    "rss_delta_mb": 10157.60546875,
    "faiss_threads": 8,
    "qps": 1260.080460341869,
    "latency_ms": 0.7924841325992019,
    "latency_p99_ms": 0.794239834917942,
    "recall_1": 0.9998,
    "recall_10": 0.99984,
    "recall_100": 0.999638,
    "n_base": 1281167,
    "study": "varyEFC"
  },
  {
    "algo": "HNSW",
    "M": 32,
    "efConstruction": 400,
    "efSearch": 10,
    "build_s": 808.1177557649935,
    "size_mb": 10341.63600730896,
    "rss_mb": 10432.1796875,
    "rss_peak_mb": 19288.20703125,
    "rss_delta_mb": 10165.671875,
    "faiss_threads": 8,
    "qps": 21791.120543502017,
    "latency_ms": 0.04590230546600651,
    "latency_p99_ms": 0.04593726591899758,
    "recall_1": 0.923,
    "recall_10": 0.88384,
    "recall_100": 0.634416,
    "n_base": 1281167,
    "study": "varyEFC"
  },
  {
    "algo": "HNSW",
    "M": 32,
    "efConstruction": 400,
    "efSearch": 20,
    "build_s": 808.1177557649935,
    "size_mb": 10341.63600730896,
    "rss_mb": 10432.1796875,
    "rss_peak_mb": 19288.20703125,
    "rss_delta_mb": 10165.671875,
    "faiss_threads": 8,
    "qps": 14381.630847023978,
    "latency_ms": 0.06970937513300063,
    "latency_p99_ms": 0.07022982167691225,
    "recall_1": 0.9728,
    "recall_10": 0.95338,
    "recall_100": 0.800286,
    "n_base": 1281167,
    "study": "varyEFC"
  },
  {
    "algo": "HNSW",
    "M": 32,
    "efConstruction": 400,
    "efSearch": 40,
    "build_s": 808.1177557649935,
    "size_mb": 10341.63600730896,
    "rss_mb": 10432.1796875,
    "rss_peak_mb": 19288.20703125,
    "rss_delta_mb": 10165.671875,
    "faiss_threads": 8,
    "qps": 8958.850326993115,
    "latency_ms": 0.11207557013258339,
    "latency_p99_ms": 0.1135285965508665,
    "recall_1": 0.9906,
    "recall_10": 0.98464,
    "recall_100": 0.923894,
    "n_base": 1281167,
    "study": "varyEFC"
  },
  {
    "algo": "HNSW",
    "M": 32,
    "efConstruction": 400,
    "efSearch": 80,
    "build_s": 808.1177557649935,
    "size_mb": 10341.63600730896,
    "rss_mb": 10432.1796875,
    "rss_peak_mb": 19288.20703125,
    "rss_delta_mb": 10165.671875,
    "faiss_threads": 8,
    "qps": 5554.4573468255685,
    "latency_ms": 0.17991747339935196,
    "latency_p99_ms": 0.18142274999251823,
    "recall_1": 0.9962,
    "recall_10": 0.99524,
    "recall_100": 0.978346,
    "n_base": 1281167,
    "study": "varyEFC"
  },
  {
    "algo": "HNSW",
    "M": 32,
    "efConstruction": 400,
    "efSearch": 160,
    "build_s": 808.1177557649935,
    "size_mb": 10341.63600730896,
    "rss_mb": 10432.1796875,
    "rss_peak_mb": 19288.20703125,
    "rss_delta_mb": 10165.671875,
    "faiss_threads": 8,
    "qps": 3336.430279079928,
    "latency_ms": 0.29945521633392974,
    "latency_p99_ms": 0.3000806751791388,
    "recall_1": 0.9988,
    "recall_10": 0.99858,
    "recall_100": 0.994892,
    "n_base": 1281167,
    "study": "varyEFC"
  },
  {
    "algo": "HNSW",
    "M": 32,
    "efConstruction": 400,
    "efSearch": 320,
    "build_s": 808.1177557649935,
    "size_mb": 10341.63600730896,
    "rss_mb": 10432.1796875,
    "rss_peak_mb": 19288.20703125,
    "rss_delta_mb": 10165.671875,
    "faiss_threads": 8,
    "qps": 1994.8122784278523,
    "latency_ms": 0.5003668299992569,
    "latency_p99_ms": 0.5017973699797295,
    "recall_1": 0.9996,
    "recall_10": 0.99958,
    "recall_100": 0.998988,
    "n_base": 1281167,
    "study": "varyEFC"
  },
  {
    "algo": "HNSW",
    "M": 32,
    "efConstruction": 400,
    "efSearch": 640,
    "build_s": 808.1177557649935,
    "size_mb": 10341.63600730896,
    "rss_mb": 10432.1796875,
    "rss_peak_mb": 19288.20703125,
    "rss_delta_mb": 10165.671875,
    "faiss_threads": 8,
    "qps": 1094.4159667526174,
    "latency_ms": 0.9148567404665906,
    "latency_p99_ms": 0.9172484421789413,
    "recall_1": 0.9998,
    "recall_10": 0.99988,
    "recall_100": 0.999814,
    "n_base": 1281167,
    "study": "varyEFC"
  }
]